[
  {
    "id": "F1",
    "priority": 1,
    "description": "プロジェクト基盤: Phaser 3 が 960x540 で起動し、Boot→Main のシーン骨格がある。verify.sh の tsc/build/vitest が green",
    "steps": ["npm run dev で起動", "canvas が表示される", "bash scripts/verify.sh が通る"],
    "passes": true
  },
  {
    "id": "F2",
    "priority": 2,
    "description": "確率抽選エンジン: design.md の役テーブルに基づく抽選を pure TS モジュールで実装。シード可能 PRNG。vitest で10万試行の分布が期待確率±30%相対誤差内",
    "steps": ["src/core/slot.ts に抽選ロジック", "tests/ に分布検証テスト", "役テーブルは定数モジュールで一元管理"],
    "passes": true
  },
  {
    "id": "F3",
    "priority": 3,
    "description": "リール表示と3段階ストップ: スピン開始で3リールが回転し、クリック/タップで順に停止。出目は抽選結果と整合（当選役が有効ライン上に並ぶ）",
    "steps": ["スピンボタンで回転開始", "3回クリックで順に停止", "抽選結果と表示出目が一致することをテスト"],
    "passes": true
  },
  {
    "id": "F4",
    "priority": 4,
    "description": "コイン経済: ベット消費、役に応じた払い出し、残高UI表示。コイン不足時はスピン不可。初期コインあり",
    "steps": ["スピンでベット分減少", "揃うと払い出し加算", "残高0でスピンボタン無効"],
    "passes": true
  },
  {
    "id": "F5",
    "priority": 5,
    "description": "天井システム: バトル非突入40スピンで次スピン突入確定。残りカウントのメーターUI表示。ロジックはテストで検証",
    "steps": ["40スピン非突入→41回目で必ず突入するテスト", "メーターが画面に表示され減っていく"],
    "passes": true
  },
  {
    "id": "F6",
    "priority": 6,
    "description": "バトルラッシュ突入: 扉図柄3揃い or 天井で Battle シーンへ移行。2リール一致時は3リール目スロー化のリーチ演出",
    "steps": ["扉3揃いでシーン遷移", "天井到達でも遷移", "リーチ時に3リール目の回転が遅くなる"],
    "passes": true
  },
  {
    "id": "F7",
    "priority": 7,
    "description": "モンスターデータモデル: 4系統（獣/ドラゴン/スライム/アンデッド）15種（隠し1種含む）をデータ駆動で定義。HP/ATK/DEF/SPD+スキル1個。プレースホルダー見た目（系統色×シルエット差）を動的テクスチャで生成、スプライトキーは1モジュールで一元管理",
    "steps": ["src/data/monsters.ts に15種定義", "系統・ステータス・スキルの整合性テスト", "各種族が画面上で見分けられる"],
    "passes": true
  },
  {
    "id": "F8",
    "priority": 8,
    "description": "自動戦闘エンジン: パーティ3体vs敵グループ、SPD順に自動で行動し勝敗が決まる pure TS モジュール。vitest でダメージ計算・勝敗判定を検証",
    "steps": ["src/core/battle.ts に戦闘ロジック", "強パーティが弱敵に勝つ/逆は負けるテスト", "Battle シーンで行動がアニメーション表示される"],
    "passes": true
  },
  {
    "id": "F9",
    "priority": 9,
    "description": "ラッシュ中スピンブースト: バトル中もスピン継続。剣3揃い=全員追撃、ハート3揃い=全員回復、星3揃い=先頭の継承スキル発動が戦闘に反映される",
    "steps": ["バトル中にスロットUIが操作できる", "各役の効果が戦闘状態に反映されるテスト", "発動時に画面上でわかる表示"],
    "passes": true
  },
  {
    "id": "F10",
    "priority": 10,
    "description": "バトル報酬と保険: 勝利で大量コイン+タマゴ+素材、敗北でも投入コイン一部+素材を持ち帰り。結果画面で内訳表示",
    "steps": ["勝利時の報酬付与テスト", "敗北時の保険付与テスト", "結果画面に内訳が出る"],
    "passes": true
  },
  {
    "id": "F11",
    "priority": 11,
    "description": "階層進行と敵スケーリング: 勝利で階層+1、階層に応じて敵ステータス強化。10階層ごとにボス（タマゴ確定ドロップ）。ハイスコア=到達階層",
    "steps": ["階層による敵強化のテスト", "10階層目がボスになる", "現在階層と最高階層がUI表示される"],
    "passes": true
  },
  {
    "id": "F12",
    "priority": 12,
    "description": "タマゴ孵化と手持ち管理: タマゴからベース4種を入手。手持ち一覧UIとパーティ3体の編成変更ができる",
    "steps": ["孵化で手持ちに追加", "育成画面で一覧表示", "パーティ入れ替えが次バトルに反映"],
    "passes": true
  },
  {
    "id": "F13",
    "priority": 13,
    "description": "配合システム: 2体選択→系統×系統の組み合わせ表で新種決定、親スキルから1個選んで継承、親消滅+基礎ステ上乗せ。レア組み合わせで隠し種。全組み合わせをテストで検証",
    "steps": ["配合UIで2体+継承スキル選択", "組み合わせ表10通り+隠し種のテスト", "子のステ上乗せ計算のテスト"],
    "passes": true
  },
  {
    "id": "F14",
    "priority": 14,
    "description": "餌やり強化: 素材を消費してモンスターのステータスを強化できる。素材種別と上昇量はデータ駆動",
    "steps": ["育成画面で素材消費→ステ上昇", "素材不足時は不可", "上昇量のテスト"],
    "passes": true
  },
  {
    "id": "F15",
    "priority": 15,
    "description": "図鑑と確率表: 発見済み種族の一覧+未発見はシルエット表示。役の確率テーブルをゲーム内で常時閲覧できる画面",
    "steps": ["図鑑画面で発見/未発見が区別される", "確率表画面に役テーブルの実値が表示される"],
    "passes": true
  },
  {
    "id": "F16",
    "priority": 16,
    "description": "目押し（取りこぼし）: フラッシュ図柄当選時にリール上で図柄が光り、タイミング押し成功で満額/失敗で半額。当選自体はスピン開始時に確定済み（結果はタイミング非依存）",
    "steps": ["フラッシュ当選時に視覚合図が出る", "成功/失敗で報酬額が変わるテスト", "当選判定がタイミングと独立であることをテストで保証"],
    "passes": false
  },
  {
    "id": "F17",
    "priority": 17,
    "description": "オートスピン: 階層5クリアで解放。ONで自動スピン+自動停止するが、目押しボーナスは常に半額（満額不可）",
    "steps": ["解放条件のテスト", "オート中は操作なしでスピンが続く", "オート中のフラッシュ役が半額になるテスト"],
    "passes": false
  },
  {
    "id": "F18",
    "priority": 18,
    "description": "セーブ/ロード: コイン・手持ち・階層・図鑑・設定を localStorage に自動保存。リロードで復帰。破損データは初期化フォールバック",
    "steps": ["状態変化後に保存される", "リロード相当の復元テスト", "不正JSONで初期化されるテスト"],
    "passes": false
  },
  {
    "id": "F19",
    "priority": 19,
    "description": "演出ジュース: ラッシュ突入カットイン、払い出しコインシャワー、画面振動、ヒットストップ、WebAudio生成SE（スピン/停止/揃い/勝利）",
    "steps": ["各演出がトリガーで再生される", "SEはWebAudioで生成（外部ファイルなし）", "演出中も操作がデッドロックしない"],
    "passes": false
  },
  {
    "id": "F20",
    "priority": 20,
    "description": "E2Eスモーク: Puppeteer で dist/ を配信して起動→スピン→（__DEBUG__フックで）ラッシュ突入→戦闘進行→結果画面到達を自動確認。verify.sh に組み込み",
    "steps": ["scripts/e2e.mjs 作成", "verify.sh から呼ばれ green", "コンソールエラー0を検証"],
    "passes": false
  },
  {
    "id": "F21",
    "priority": 21,
    "description": "リリース成果物: npm run build で itch.io アップロード可能な dist/ 一式（相対パス動作）。zip化スクリプトと操作説明README",
    "steps": ["dist/index.html をfile://以外の静的サーバで開いて動作", "scripts/package.sh で zip 生成", "README.md に操作説明とクレジット欄"],
    "passes": false
  }
]
